odoo8_addon_membership_initial_fee-8.0.1.0.0.99.dev21-py3.8-nspkg.pth
odoo_addons/membership_initial_fee/README.rst
odoo_addons/membership_initial_fee/__init__.py
odoo_addons/membership_initial_fee/__openerp__.py
odoo_addons/membership_initial_fee/i18n/ca.po
odoo_addons/membership_initial_fee/i18n/de.po
odoo_addons/membership_initial_fee/i18n/es.po
odoo_addons/membership_initial_fee/i18n/es_MX.po
odoo_addons/membership_initial_fee/i18n/fi.po
odoo_addons/membership_initial_fee/i18n/fr.po
odoo_addons/membership_initial_fee/i18n/fr_CH.po
odoo_addons/membership_initial_fee/i18n/hr.po
odoo_addons/membership_initial_fee/i18n/hr_HR.po
odoo_addons/membership_initial_fee/i18n/it.po
odoo_addons/membership_initial_fee/i18n/membership_initial_fee.pot
odoo_addons/membership_initial_fee/i18n/nl_NL.po
odoo_addons/membership_initial_fee/i18n/pt_BR.po
odoo_addons/membership_initial_fee/i18n/pt_PT.po
odoo_addons/membership_initial_fee/i18n/ro.po
odoo_addons/membership_initial_fee/i18n/sl.po
odoo_addons/membership_initial_fee/i18n/tr.po
odoo_addons/membership_initial_fee/i18n/tr_TR.po
odoo_addons/membership_initial_fee/i18n/vi_VN.po
odoo_addons/membership_initial_fee/i18n/zh_CN.po
odoo_addons/membership_initial_fee/models/__init__.py
odoo_addons/membership_initial_fee/models/account_invoice.py
odoo_addons/membership_initial_fee/models/product_template.py
odoo_addons/membership_initial_fee/static/description/icon.png
odoo_addons/membership_initial_fee/static/description/icon.svg
odoo_addons/membership_initial_fee/tests/__init__.py
odoo_addons/membership_initial_fee/tests/test_membership_initial_fee.py
odoo_addons/membership_initial_fee/views/product_template_views.xml
odoo8_addon_membership_initial_fee-8.0.1.0.0.99.dev21.dist-info/METADATA
odoo8_addon_membership_initial_fee-8.0.1.0.0.99.dev21.dist-info/WHEEL
odoo8_addon_membership_initial_fee-8.0.1.0.0.99.dev21.dist-info/namespace_packages.txt
odoo8_addon_membership_initial_fee-8.0.1.0.0.99.dev21.dist-info/top_level.txt
odoo8_addon_membership_initial_fee-8.0.1.0.0.99.dev21.dist-info/RECORD
